PyImarisWriter/ImarisWriterCtypes.py
PyImarisWriter/PyImarisWriter.py
PyImarisWriter/__init__.py
PyImarisWriter/bpImarisWriter96.dll
PyImarisWriter/hdf5.dll
PyImarisWriter/zlib.dll
PyImarisWriter-0.7.0.dist-info/LICENSE.txt
PyImarisWriter-0.7.0.dist-info/METADATA
PyImarisWriter-0.7.0.dist-info/WHEEL
PyImarisWriter-0.7.0.dist-info/top_level.txt
PyImarisWriter-0.7.0.dist-info/RECORD
