Metadata-Version: 2.1
Name: PyImarisWriter
Version: 0.7.0
Summary: Python wrapper for ImarisWriter library
Home-page: https://github.com/imaris/ImarisWriter
Author: Imaris
Author-email: sacha@bitplane.com
License: Apache License, Version 2.0
Platform: UNKNOWN
Classifier: Programming Language :: Python :: 3
Classifier: License :: OSI Approved :: Apache Software License
Classifier: Operating System :: Microsoft :: Windows
Requires-Python: >=3.6
License-File: LICENSE.txt
